mt_awscdk_constructs/__init__.py
mt_awscdk_constructs/py.typed
mt_awscdk_constructs/_jsii/__init__.py
mt_awscdk_constructs/_jsii/mt-awscdk-constructs@0.0.13.jsii.tgz
mt_awscdk_constructs-0.0.13.dist-info/LICENSE
mt_awscdk_constructs-0.0.13.dist-info/METADATA
mt_awscdk_constructs-0.0.13.dist-info/WHEEL
mt_awscdk_constructs-0.0.13.dist-info/top_level.txt
mt_awscdk_constructs-0.0.13.dist-info/RECORD
