Metadata-Version: 2.1
Name: mt-awscdk-constructs
Version: 0.0.13
Summary: Marley Tech AWS CDK Construct Library
Home-page: https://github.com/marleytech/mt-awscdk-constructs.git
Author: Greg Farrow<g-farrow@users.noreply.github.com>
License: MIT
Project-URL: Source, https://github.com/marleytech/mt-awscdk-constructs.git
Platform: UNKNOWN
Classifier: Intended Audience :: Developers
Classifier: Operating System :: OS Independent
Classifier: Programming Language :: JavaScript
Classifier: Programming Language :: Python :: 3 :: Only
Classifier: Programming Language :: Python :: 3.6
Classifier: Programming Language :: Python :: 3.7
Classifier: Programming Language :: Python :: 3.8
Classifier: Programming Language :: Python :: 3.9
Classifier: Typing :: Typed
Classifier: Development Status :: 5 - Production/Stable
Classifier: License :: OSI Approved
Requires-Python: >=3.6
License-File: LICENSE
Requires-Dist: aws-cdk.aws-cloudwatch-actions (<2.0.0,>=1.109.0)
Requires-Dist: aws-cdk.aws-cloudwatch (<2.0.0,>=1.109.0)
Requires-Dist: aws-cdk.aws-events-targets (<2.0.0,>=1.109.0)
Requires-Dist: aws-cdk.aws-events (<2.0.0,>=1.109.0)
Requires-Dist: aws-cdk.aws-lambda (<2.0.0,>=1.109.0)
Requires-Dist: aws-cdk.aws-sns (<2.0.0,>=1.109.0)
Requires-Dist: aws-cdk.aws-sqs (<2.0.0,>=1.109.0)
Requires-Dist: aws-cdk.core (<2.0.0,>=1.109.0)
Requires-Dist: constructs (<4.0.0,>=3.2.27)
Requires-Dist: jsii (<2.0.0,>=1.47.0)
Requires-Dist: publication (>=0.0.3)
